glazari_test-0.1.0.dist-info/METADATA
glazari_test-0.1.0.dist-info/WHEEL
glazari_test/__init__.py
glazari_test/glazari_test.abi3.so
glazari_test-0.1.0.dist-info/RECORD
