Metadata-Version: 2.1
Name: glazari-test
Version: 0.1.0
